fightbender/__init__.py
fightbender/generators/__init__.py
fightbender/generators/linear.py
fightbender-0.0.2.dist-info/METADATA
fightbender-0.0.2.dist-info/WHEEL
fightbender-0.0.2.dist-info/top_level.txt
fightbender-0.0.2.dist-info/RECORD
