Metadata-Version: 2.1
Name: fightbender
Version: 0.0.2
Summary: MMA DFS Toolkit
Home-page: UNKNOWN
Author: Brandin Canfield
Author-email: <brandincanfield@gmail.com>
License: UNKNOWN
Keywords: mma,dfs,lineup,optimizer,generator
Platform: UNKNOWN
Classifier: Programming Language :: Python :: 3
